{
  "pools": [
    {
      "rolls": 3,
      "bonus_rolls": 1,
      "entries": [
        {
          "type": "minecraft:loot_table",
          "weight": 2,
          "value": "infinity_cave:refs/rare_gear"
        },
        {
          "type": "minecraft:loot_table",
          "weight": 2,
          "value": "infinity_cave:refs/mushroom/rare"
        },
        {
          "type": "minecraft:item",
          "weight": 2,
          "name": "minecraft:cooked_beef",
          "functions": [
            {
              "function": "minecraft:set_count",
              "count": {
                "min": 1,
                "max": 2
              }
            }
          ]
        },
        {
          "type": "minecraft:item",
          "weight": 2,
          "name": "minecraft:leather",
          "functions": [
            {
              "function": "minecraft:set_count",
              "count": {
                "min": 1,
                "max": 2
              }
            }
          ]
        }
      ]
    },
    {
      "rolls": 2,
      "entries": [
        {
          "type": "item",
          "name": "golden_apple"
        },
        {
          "type": "item",
          "name": "enchanted_golden_apple",
          "conditions": [
            {
              "condition": "random_chance",
              "chance": 0.075
            }
          ]
        }
      ]
    }
  ]
}
